pymlx/__init__.py
pymlx/core.py
pymlx/evaluation.py
pymlx/features_handler.py
pymlx/featurizer.py
pymlx/model.py
pymlx/parameter_sweep.py
pymlx/test.py
pymlx/utils.py
pymlx/visualization.py
pymlx-0.1.1.dist-info/METADATA
pymlx-0.1.1.dist-info/RECORD
pymlx-0.1.1.dist-info/WHEEL
pymlx-0.1.1.dist-info/top_level.txt
